ErlangBianchengGuize/README.md
ErlangBianchengGuize/__init__.py
ErlangBianchengGuize/__main__.py
ErlangBianchengGuize/file.epub
ErlangBianchengGuize/index.html
ErlangBianchengGuize/css/__init__.py
ErlangBianchengGuize/css/annotations.css
ErlangBianchengGuize/css/main.css
ErlangBianchengGuize/css/normalize.css
ErlangBianchengGuize/css/popup.css
ErlangBianchengGuize/font/__init__.py
ErlangBianchengGuize/font/fontello.eot
ErlangBianchengGuize/font/fontello.svg
ErlangBianchengGuize/font/fontello.ttf
ErlangBianchengGuize/font/fontello.woff
ErlangBianchengGuize/img/__init__.py
ErlangBianchengGuize/img/annotator-glyph-sprite.png
ErlangBianchengGuize/img/annotator-icon-sprite.png
ErlangBianchengGuize/img/apple-touch-icon.png
ErlangBianchengGuize/img/cancelfullscreen.png
ErlangBianchengGuize/img/close.png
ErlangBianchengGuize/img/fullscreen.png
ErlangBianchengGuize/img/loader.gif
ErlangBianchengGuize/img/menu-icon.png
ErlangBianchengGuize/img/save.png
ErlangBianchengGuize/img/saved.png
ErlangBianchengGuize/img/settings-s.png
ErlangBianchengGuize/img/settings.png
ErlangBianchengGuize/img/star.png
ErlangBianchengGuize/js/__init__.py
ErlangBianchengGuize/js/epub.js
ErlangBianchengGuize/js/epub.min.js
ErlangBianchengGuize/js/epub.min.map
ErlangBianchengGuize/js/hooks.min.js
ErlangBianchengGuize/js/hooks.min.map
ErlangBianchengGuize/js/reader.js
ErlangBianchengGuize/js/reader.js.map
ErlangBianchengGuize/js/reader.min.js
ErlangBianchengGuize/js/reader.min.map
ErlangBianchengGuize/js/hooks/__init__.py
ErlangBianchengGuize/js/hooks/extensions/__init__.py
ErlangBianchengGuize/js/hooks/extensions/highlight.js
ErlangBianchengGuize/js/libs/__init__.py
ErlangBianchengGuize/js/libs/jquery.min.js
ErlangBianchengGuize/js/libs/localforage.min.js
ErlangBianchengGuize/js/libs/screenfull.js
ErlangBianchengGuize/js/libs/screenfull.min.js
ErlangBianchengGuize/js/libs/zip.min.js
ErlangBianchengGuize/js/plugins/__init__.py
ErlangBianchengGuize/js/plugins/hypothesis.js
erlang_biancheng_guize-2024.3.3.0.dist-info/METADATA
erlang_biancheng_guize-2024.3.3.0.dist-info/WHEEL
erlang_biancheng_guize-2024.3.3.0.dist-info/entry_points.txt
erlang_biancheng_guize-2024.3.3.0.dist-info/top_level.txt
erlang_biancheng_guize-2024.3.3.0.dist-info/RECORD
